superutils
