Metadata-Version: 2.1
Name: superutils
Version: 0.1.0
Summary: The super superutils makes the code simpler!
Home-page: https://github.com/YouAreOnlyOne
Author: Frank YCJ
Author-email: 1320259466@qq.com
License: Apache 2.0 license
Project-URL: Bug Tracker, https://github.com/YouAreOnlyOne/FastFrameJar/issues
Project-URL: Documentation, https://github.com/YouAreOnlyOne/FastFrameJar
Project-URL: Source Code, https://github.com/YouAreOnlyOne/FastFrameJar
Keywords: super utils code simpler box email json security
Platform: UNKNOWN
Classifier: Programming Language :: Python :: 2
Classifier: License :: OSI Approved :: MIT License
Classifier: Operating System :: OS Independent
Requires-Python: >=2.4
